chia_bech32m/__init__.py
chia_bech32m/bech32m.py
chia_bech32m-1.0.0.dist-info/LICENSE
chia_bech32m-1.0.0.dist-info/METADATA
chia_bech32m-1.0.0.dist-info/WHEEL
chia_bech32m-1.0.0.dist-info/top_level.txt
chia_bech32m-1.0.0.dist-info/RECORD
