Metadata-Version: 2.1
Name: chia-bech32m
Version: 1.0.0
Summary: A BIP350 compatible Bech32m encoding/decoding library for chia.
Author-email: hezuoshe <nongyehezuoshe@gmail.com>
Project-URL: Homepage, https://github.com/nongyehezuoshe/chia-bech32m
Project-URL: Bug Tracker, https://github.com/nongyehezuoshe/chia-bech32m/issues
Requires-Python: >=3.0
License-File: LICENSE
